RBComb/LaserInterface.py
RBComb/RBComb576.py
RBComb/SerialBridge.py
RBComb/__init__.py
RBComb/Helper/BoardPinout.py
RBComb/Helper/BoardUnits.py
RBComb/Helper/FunctionInterpolator.py
RBComb/Helper/__init__.py
rbcomb-0.2.0.dist-info/METADATA
rbcomb-0.2.0.dist-info/WHEEL
rbcomb-0.2.0.dist-info/top_level.txt
rbcomb-0.2.0.dist-info/RECORD
